face_crop_plus/__init__.py
face_crop_plus/__main__.py
face_crop_plus/cropper.py
face_crop_plus/utils.py
face_crop_plus/models/__init__.py
face_crop_plus/models/_layers.py
face_crop_plus/models/bise.py
face_crop_plus/models/retinaface.py
face_crop_plus/models/rrdb.py
face_crop_plus-1.1.0.dist-info/LICENCE
face_crop_plus-1.1.0.dist-info/METADATA
face_crop_plus-1.1.0.dist-info/WHEEL
face_crop_plus-1.1.0.dist-info/entry_points.txt
face_crop_plus-1.1.0.dist-info/top_level.txt
face_crop_plus-1.1.0.dist-info/RECORD
