Metadata-Version: 2.1
Name: face-crop-plus
Version: 1.1.0
Summary: Automatic face aligner and cropper with quality enhancement and attribute parsing.
Home-page: https://github.com/mantasu/face-crop-plus
Author: Mantas Birškus
Author-email: mantix7@gmail.com
License: MIT
Project-URL: Documentation, https://mantasu.github.io/face-crop-plus
Project-URL: Bug Tracker, https://github.com/mantasu/face-crop-plus/issues
Keywords: face,python,pytorch,alignment,cropping,super resolution,quality enhancement,parsing,grouping,attributes,mask,segmentation,celeba
Classifier: Intended Audience :: Science/Research
Classifier: Intended Audience :: Developers
Classifier: Programming Language :: Python :: 3
Classifier: Programming Language :: Python :: 3.10
Classifier: Programming Language :: Python :: 3.11
Classifier: License :: OSI Approved :: MIT License
Classifier: Operating System :: OS Independent
Classifier: Topic :: Software Development :: Libraries :: Python Modules
Requires-Python: >=3.10
License-File: LICENCE
Requires-Dist: tqdm
Requires-Dist: unidecode
Requires-Dist: opencv-python
Requires-Dist: torch
Requires-Dist: torchvision
